{
  "vendors.js": "/gls/static/js/vendors.69febf4a.js",
  "vendors.js.map": "/gls/static/js/vendors.4d4991e17703c1ec545f.js.map",
  "src-docs-common-common-types~src-docs-components-responsive~src-docs-components-spacers~src-docs-com~3c01953b.js": "/gls/static/js/src-docs-common-common-types~src-docs-components-responsive~src-docs-components-spacers~src-docs-com~3c01953b.c053dc9d.js",
  "src-docs-common-common-types~src-docs-components-responsive~src-docs-components-spacers~src-docs-com~3c01953b.js.map": "/gls/static/js/src-docs-common-common-types~src-docs-components-responsive~src-docs-components-spacers~src-docs-com~3c01953b.4d4991e17703c1ec545f.js.map",
  "app.js": "/gls/static/js/app.4d4991e17703c1ec545f.js",
  "app.js.map": "/gls/static/js/app.4d4991e17703c1ec545f.js.map",
  "src-docs-common-common-types.js": "/gls/static/js/src-docs-common-common-types.dea9e8b7.js",
  "src-docs-common-common-types.js.map": "/gls/static/js/src-docs-common-common-types.4d4991e17703c1ec545f.js.map",
  "src-docs-components-responsive.js": "/gls/static/js/src-docs-components-responsive.0da0612b.js",
  "src-docs-components-responsive.js.map": "/gls/static/js/src-docs-components-responsive.4d4991e17703c1ec545f.js.map",
  "src-docs-components-spacers.js": "/gls/static/js/src-docs-components-spacers.31b70a2d.js",
  "src-docs-components-spacers.js.map": "/gls/static/js/src-docs-components-spacers.4d4991e17703c1ec545f.js.map",
  "src-docs-components-vertical.js": "/gls/static/js/src-docs-components-vertical.81d9ceba.js",
  "src-docs-components-vertical.js.map": "/gls/static/js/src-docs-components-vertical.4d4991e17703c1ec545f.js.map",
  "src-docs-index.js": "/gls/static/js/src-docs-index.51e0017d.js",
  "src-docs-index.js.map": "/gls/static/js/src-docs-index.4d4991e17703c1ec545f.js.map",
  "src-docs-principles-scrolling.js": "/gls/static/js/src-docs-principles-scrolling.4b452dde.js",
  "src-docs-principles-scrolling.js.map": "/gls/static/js/src-docs-principles-scrolling.4d4991e17703c1ec545f.js.map",
  "src-docs-principles-sizing.js": "/gls/static/js/src-docs-principles-sizing.c7b5c6ec.js",
  "src-docs-principles-sizing.js.map": "/gls/static/js/src-docs-principles-sizing.4d4991e17703c1ec545f.js.map",
  "src-docs-principles-spacing.js": "/gls/static/js/src-docs-principles-spacing.53102881.js",
  "src-docs-principles-spacing.js.map": "/gls/static/js/src-docs-principles-spacing.4d4991e17703c1ec545f.js.map",
  "index.html": "/gls/index.html",
  "static/img/margincollapse.png": "/gls/static/img/margincollapse.5e3abf25.png",
  "static/img/marginplacement.png": "/gls/static/img/marginplacement.e27ea215.png"
}